LICENSE
README.md
setup.py
nodered_forge/__init__.py
nodered_forge/app.py
nodered_forge/conf.py
nodered_forge/input.py
nodered_forge/node.py
nodered_forge/templating.py
nodered_forge/type_hints.py
nodered_forge/utils.py
nodered_forge.egg-info/PKG-INFO
nodered_forge.egg-info/SOURCES.txt
nodered_forge.egg-info/dependency_links.txt
nodered_forge.egg-info/requires.txt
nodered_forge.egg-info/top_level.txt
nodered_forge/templates/static/node.html
nodered_forge/templates/static/node.js