Metadata-Version: 2.1
Name: nodered-forge
Version: 1.0.0
Summary: NodeRedForge is a Python-based tool designed to facilitate the generation of custom JSON API nodes for Node-RED. By Khalid Grandi (github.com/xaled).
Home-page: https://github.com/xaled/nodered-forge
Author: Khalid Grandi
Author-email: kh.grandi@gmail.com
License: MIT
Keywords: library node-red code-generator
Classifier: License :: OSI Approved :: MIT License
Classifier: Operating System :: OS Independent
Classifier: Programming Language :: Python
Requires-Python: >=3
License-File: LICENSE
